LICENSE.txt
MANIFEST.in
README.md
requirements.txt
setup.cfg
setup.py
openstackinfo/__init__.py
openstackinfo/entrypoint.py
openstackinfo/helpers.py
openstackinfo/indexers.py
openstackinfo/schema.py
openstackinfo.egg-info/PKG-INFO
openstackinfo.egg-info/SOURCES.txt
openstackinfo.egg-info/dependency_links.txt
openstackinfo.egg-info/entry_points.txt
openstackinfo.egg-info/requires.txt
openstackinfo.egg-info/top_level.txt
openstackinfo/retriever/__init__.py
openstackinfo/retriever/helpers.py
openstackinfo/retriever/models.py
openstackinfo/retriever/retrievers.py
openstackinfo/tests/__init__.py
openstackinfo/tests/_common.py
openstackinfo/tests/test_entrypoint.py
openstackinfo/tests/test_helpers.py
openstackinfo/tests/test_indexers.py
openstackinfo/tests/test_schema.py
openstackinfo/tests/retriever/__init__.py
openstackinfo/tests/retriever/test_helpers.py
openstackinfo/tests/retriever/test_retrievers.py