Metadata-Version: 1.0
Name: openstackinfo
Version: 5.4.0
Summary: Gets information about what is in an OpenStack tenant
Home-page: https://github.com/wtsi-hgi/openstack-info
Author: UNKNOWN
Author-email: UNKNOWN
License: MIT
Platform: UNKNOWN
